libjob/__init__.py
libjob/py.typed
libjob-0.1.3.dist-info/METADATA
libjob-0.1.3.dist-info/WHEEL
libjob-0.1.3.dist-info/licenses/COPYING
libjob-0.1.3.dist-info/licenses/COPYING.LESSER
libjob-0.1.3.dist-info/RECORD
