Metadata-Version: 2.3
Name: libjob
Version: 0.1.3
Summary: Python warpper of the Windows job feature, replacement of the resource library
Project-URL: Repository, https://github.com/colinxu2020/libjob
Project-URL: Issues, https://github.com/colinxu2020/libjob/issues
Project-URL: Changelog, https://github.com/colinxu2020/libjob/ blob/master/CHANGELOG.md
Author-email: Colinxu2020 <colinxu2020@gmail.com>
Keywords: job,resource,win32,windows
Classifier: Development Status :: 4 - Beta
Classifier: Environment :: Win32 (MS Windows)
Classifier: Intended Audience :: Developers
Classifier: License :: OSI Approved :: GNU Lesser General Public License v3 or later (LGPLv3+)
Classifier: Operating System :: Microsoft :: Windows
Classifier: Programming Language :: Python
Classifier: Programming Language :: Python :: 3
Classifier: Programming Language :: Python :: 3 :: Only
Classifier: Programming Language :: Python :: 3.7
Classifier: Programming Language :: Python :: 3.8
Classifier: Programming Language :: Python :: 3.9
Classifier: Programming Language :: Python :: 3.10
Classifier: Programming Language :: Python :: 3.11
Classifier: Programming Language :: Python :: 3.12
Classifier: Programming Language :: Python :: 3.13
Classifier: Topic :: Software Development :: Libraries
Requires-Python: >=3.7
Requires-Dist: pywin32>=308
